hdltools/__init__.py
hdltools/codetests.py
hdltools/compare_profiles.py
hdltools/constants.py
hdltools/csv2delta.py
hdltools/dsapi.py
hdltools/dsclient.py
hdltools/hdlcatalog.py
hdltools/hdldeltatable.py
hdltools/hdlfiles.py
hdltools/hdlfsapi.py
hdltools/hdlgendata.py
hdltools/hdlgendataspark.py
hdltools/hdlinstance.py
hdltools/hdlord.py
hdltools/hdlpolicy.py
hdltools/hdlshare.py
hdltools/pycsn.py
hdltools/sapcert.py
hdltools/smoketest.py
hdltools/termprint.py
hdltools/to_hana.py
hdltools-0.1.2.dist-info/METADATA
hdltools-0.1.2.dist-info/WHEEL
hdltools-0.1.2.dist-info/entry_points.txt
hdltools-0.1.2.dist-info/RECORD
