Metadata-Version: 2.3
Name: hdltools
Version: 0.1.2
Summary: HDL Delta Sharing Utilities
Project-URL: Documentation, https://github.tools.sap/hda-xpm-frontrunner/hdltools#readme
Project-URL: Issues, https://github.tools.sap/hda-xpm-frontrunner/hdltools/issues
Project-URL: Source, https://github.tools.sap/hda-xpm-frontrunner/hdltools
Author-email: Thorsten Hapke <thorsten.hapke@sap.com>
License-Expression: MIT
Classifier: Development Status :: 4 - Beta
Classifier: Programming Language :: Python
Classifier: Programming Language :: Python :: 3.10
Classifier: Programming Language :: Python :: 3.11
Classifier: Programming Language :: Python :: Implementation :: CPython
Classifier: Programming Language :: Python :: Implementation :: PyPy
Requires-Python: >=3.7
Requires-Dist: cryptography
Requires-Dist: delta-sharing
Requires-Dist: pandas
Requires-Dist: pycsn
Requires-Dist: pyhdlfs
Requires-Dist: pyjwt
Requires-Dist: pyyaml
Requires-Dist: rich
